falcon_evaluate/__init__.py
falcon_evaluate/context_relevancy.py
falcon_evaluate/evaluate.py
falcon_evaluate/fairness.py
falcon_evaluate/fevaluate_plot.py
falcon_evaluate/fevaluate_reliability.py
falcon_evaluate/fevaluate_results.py
falcon_evaluate/machine_ethics.py
falcon_evaluate/security.py
falcon_evaluate/user_analytics.py
falcon_evaluate/utils.py
falcon_evaluate-0.1.13.0.dist-info/LICENSE
falcon_evaluate-0.1.13.0.dist-info/METADATA
falcon_evaluate-0.1.13.0.dist-info/WHEEL
falcon_evaluate-0.1.13.0.dist-info/RECORD
