Metadata-Version: 2.1
Name: falcon-evaluate
Version: 0.1.13.0
Summary: Falcon Evaluate is an open-source Python library designed to simplify the process of evaluating and validating open source LLM models such as llama2,mistral ,etc. This library aims to provide an easy-to-use toolkit for assessing the performance, bias, and general behavior of LLMs in various natural language understanding (NLU) tasks.
License: MIT
Author: Praveen Govindaraj
Author-email: praveengovi.analytics@gmail.com
Requires-Python: >=3.8,<4.0
Classifier: License :: OSI Approved :: MIT License
Classifier: Programming Language :: Python :: 3
Classifier: Programming Language :: Python :: 3.8
Classifier: Programming Language :: Python :: 3.9
Classifier: Programming Language :: Python :: 3.10
Classifier: Programming Language :: Python :: 3.11
Classifier: Programming Language :: Python :: 3.12
Requires-Dist: nltk (>=3.8.1,<4.0.0)
Requires-Dist: numpy (>=1.23.0,<1.24.0)
Requires-Dist: pandas (<2.0)
Requires-Dist: plotly (>=5.17.0,<6.0.0)
Requires-Dist: scikit-learn (>=1.3.1,<2.0.0)
Requires-Dist: scipy (>=1.7,<2.0)
Requires-Dist: sentence-transformers (>=2.2.2,<3.0.0)
Requires-Dist: textstat (>=0.7.3,<0.8.0)
Requires-Dist: torch (>=2.1.0,<3.0.0)
Requires-Dist: transformers (>=4.34.1,<5.0.0)
